tusk/__init__.py
tusk/drift/__init__.py
tusk/drift/backend/__init__.py
tusk/drift/backend/v1/__init__.py
tusk/drift/core/__init__.py
tusk/drift/core/v1/__init__.py
tusk/drift/instrumentation/__init__.py
tusk/drift/instrumentation/postgresql/__init__.py
tusk/drift/instrumentation/postgresql/v1/__init__.py
tusk_drift_schemas-0.1.30.dist-info/METADATA
tusk_drift_schemas-0.1.30.dist-info/WHEEL
tusk_drift_schemas-0.1.30.dist-info/top_level.txt
tusk_drift_schemas-0.1.30.dist-info/RECORD
