Metadata-Version: 2.4
Name: tusk-drift-schemas
Version: 0.1.30
Summary: Protocol Buffer schemas for Tusk Drift
Author-email: Use Tusk <support@usetusk.ai>
License-Expression: MIT
Project-URL: Homepage, https://github.com/Use-Tusk/tusk-drift-schemas
Project-URL: Repository, https://github.com/Use-Tusk/tusk-drift-schemas
Project-URL: Issues, https://github.com/Use-Tusk/tusk-drift-schemas/issues
Keywords: protobuf,grpc,tusk,drift,schemas
Classifier: Development Status :: 4 - Beta
Classifier: Intended Audience :: Developers
Classifier: Programming Language :: Python :: 3
Classifier: Programming Language :: Python :: 3.8
Classifier: Programming Language :: Python :: 3.9
Classifier: Programming Language :: Python :: 3.10
Classifier: Programming Language :: Python :: 3.11
Classifier: Programming Language :: Python :: 3.12
Classifier: Topic :: Software Development :: Libraries :: Python Modules
Requires-Python: >=3.8
Requires-Dist: betterproto[compiler]>=2.0.0b7
